lightct/__init__.py
lightct/load_scan.py
lightct/plot_funcs.py
lightct/tomo_scan.py
lightct-0.1.0.data/scripts/interactive_lightct.py
lightct-0.1.0.data/scripts/interactive_reload.py
lightct-0.1.0.dist-info/DESCRIPTION.rst
lightct-0.1.0.dist-info/METADATA
lightct-0.1.0.dist-info/RECORD
lightct-0.1.0.dist-info/WHEEL
lightct-0.1.0.dist-info/metadata.json
lightct-0.1.0.dist-info/top_level.txt
