Metadata-Version: 2.0
Name: lightct
Version: 0.1.0
Summary: Visual light computed tomography.
Home-page: https://github.com/casimp/lightct
Author: C. Simpson, L.Courtois
Author-email: c.a.simpson01@gmail.com
License: LICENSE.txt
Download-URL: https://github.com/casimp/lightct/tarball/0.1
Keywords: ct,vlct,computed tomography
Platform: UNKNOWN
Classifier: Development Status :: 3 - Alpha
Classifier: License :: OSI Approved :: MIT License
Classifier: Programming Language :: Python :: 2.7
Classifier: Programming Language :: Python :: 3.4
Classifier: Programming Language :: Python :: 3.5
Classifier: Operating System :: MacOS :: MacOS X
Classifier: Operating System :: Microsoft :: Windows
